django_find_view/__init__.py
django_find_view/__main__.py
django_find_view-0.1.0.dist-info/METADATA
django_find_view-0.1.0.dist-info/WHEEL
django_find_view-0.1.0.dist-info/entry_points.txt
django_find_view-0.1.0.dist-info/top_level.txt
django_find_view-0.1.0.dist-info/RECORD
