Metadata-Version: 2.2
Name: django-find-view
Version: 0.1.0
Summary: A small CLI tool that locates the file containing a Django view function for a given named URL
Requires-Python: >=3.12
Requires-Dist: django
